setup.cfg
setup.py
sgcontrol/__init__.py
sgcontrol/__main__.py
sgcontrol/sgcontrol.py
sgcontrol.egg-info/PKG-INFO
sgcontrol.egg-info/SOURCES.txt
sgcontrol.egg-info/dependency_links.txt
sgcontrol.egg-info/entry_points.txt
sgcontrol.egg-info/requires.txt
sgcontrol.egg-info/top_level.txt