Metadata-Version: 1.1
Name: sgcontrol
Version: 0.5.9
Summary: Foolproof AWS security group management
Home-page: https://github.com/nmasur/sgcontrol
Author: Noah Masur
Author-email: nmasur@wesleyan.edu
License: UNKNOWN
Download-URL: https://github.com/nmasur/sgcontrol/archive/0.5.9.tar.gz
Keywords: aws,aws-security,devops
Platform: UNKNOWN
